pyzxing/__init__.py
pyzxing/__version__.py
pyzxing/config.py
pyzxing/platform_utils.py
pyzxing/reader.py
pyzxing/utils.py
pyzxing-1.0.3.dist-info/licenses/LICENSE.txt
src/__init__.py
pyzxing-1.0.3.dist-info/METADATA
pyzxing-1.0.3.dist-info/WHEEL
pyzxing-1.0.3.dist-info/top_level.txt
pyzxing-1.0.3.dist-info/RECORD
