Metadata-Version: 2.4
Name: pyzxing
Version: 1.0.3
Summary: Python wrapper for ZXing Java library.
Home-page: https://github.com/ChenjieXu/pyzxing
Author: Chenjie Xu
Author-email: cxuscience@gmail.com
License: MIT
Classifier: Development Status :: 5 - Production/Stable
Classifier: Intended Audience :: Developers
Classifier: Intended Audience :: Financial and Insurance Industry
Classifier: License :: OSI Approved :: MIT License
Classifier: Operating System :: Microsoft :: Windows
Classifier: Operating System :: POSIX :: Linux
Classifier: Programming Language :: Python :: 3
Classifier: Topic :: Software Development :: Libraries
Classifier: Topic :: Software Development :: Libraries :: Python Modules
Requires-Python: >=3.8.0
License-File: LICENSE.txt
Requires-Dist: setuptools
Requires-Dist: joblib
Requires-Dist: numpy
Requires-Dist: pytest>=6.0.0
Requires-Dist: pytest-cov>=2.0.0
Requires-Dist: psutil>=5.0.0
Dynamic: author
Dynamic: author-email
Dynamic: classifier
Dynamic: description
Dynamic: description-content-type
Dynamic: home-page
Dynamic: license
Dynamic: license-file
Dynamic: requires-dist
Dynamic: requires-python
Dynamic: summary
